django_htcpcp_tea/__init__.py
django_htcpcp_tea/admin.py
django_htcpcp_tea/apps.py
django_htcpcp_tea/decorators.py
django_htcpcp_tea/fixtures/demo_forbidden_combinations.json
django_htcpcp_tea/fixtures/demo_pots.json
django_htcpcp_tea/fixtures/rfc_2324_additions.json
django_htcpcp_tea/fixtures/rfc_7168_additions.json
django_htcpcp_tea/fixtures/rfc_7168_teas.json
django_htcpcp_tea/middleware.py
django_htcpcp_tea/migrations/0001_initial.py
django_htcpcp_tea/migrations/0002_auto_20190619_1041.py
django_htcpcp_tea/migrations/0003_auto_20190620_1205.py
django_htcpcp_tea/migrations/0004_addition_type.py
django_htcpcp_tea/migrations/0005_forbiddencombination.py
django_htcpcp_tea/migrations/__init__.py
django_htcpcp_tea/models.py
django_htcpcp_tea/settings.py
django_htcpcp_tea/templates/django_htcpcp_tea/400.html
django_htcpcp_tea/templates/django_htcpcp_tea/403.html
django_htcpcp_tea/templates/django_htcpcp_tea/406.html
django_htcpcp_tea/templates/django_htcpcp_tea/418.html
django_htcpcp_tea/templates/django_htcpcp_tea/503.html
django_htcpcp_tea/templates/django_htcpcp_tea/base.html
django_htcpcp_tea/templates/django_htcpcp_tea/base_beverage.html
django_htcpcp_tea/templates/django_htcpcp_tea/base_error.html
django_htcpcp_tea/templates/django_htcpcp_tea/brewing.html
django_htcpcp_tea/templates/django_htcpcp_tea/finished.html
django_htcpcp_tea/templates/django_htcpcp_tea/includes/additions.html
django_htcpcp_tea/templates/django_htcpcp_tea/includes/alternatives.html
django_htcpcp_tea/templates/django_htcpcp_tea/options.html
django_htcpcp_tea/templates/django_htcpcp_tea/pouring.html
django_htcpcp_tea/urls.py
django_htcpcp_tea/utils.py
django_htcpcp_tea/views.py
django_htcpcp_tea-0.8.1.dist-info/LICENSE
django_htcpcp_tea-0.8.1.dist-info/METADATA
django_htcpcp_tea-0.8.1.dist-info/WHEEL
django_htcpcp_tea-0.8.1.dist-info/RECORD
