Metadata-Version: 2.1
Name: django-htcpcp-tea
Version: 0.8.1
Summary: Django app implementing HTCPCP-TEA as defined in RFC 7168.
Home-page: https://github.com/blueschu/django-htcpcp-tea
License: MIT
Keywords: htcpcp,django,rfc-2324,rfc-7168,coffee,tea
Author: Brian Schubert
Author-email: brianm.schubert@gmail.com
Requires-Python: >=3.8,<4.0
Classifier: Development Status :: 4 - Beta
Classifier: Environment :: Web Environment
Classifier: Framework :: Django
Classifier: Framework :: Django :: 2.0
Classifier: Framework :: Django :: 2.1
Classifier: Framework :: Django :: 2.2
Classifier: Intended Audience :: Developers
Classifier: License :: OSI Approved :: MIT License
Classifier: Operating System :: OS Independent
Classifier: Programming Language :: Python :: 3
Classifier: Programming Language :: Python :: 3.8
Classifier: Programming Language :: Python :: 3.9
Classifier: Programming Language :: Python :: 3.10
Classifier: Programming Language :: Python :: 3.11
Classifier: Topic :: Internet :: WWW/HTTP
Classifier: Topic :: Software Development :: Libraries :: Python Modules
Requires-Dist: django (>=2.0,<3.0)
Project-URL: Documentation, https://django-htcpcp-tea.readthedocs.io/en/latest/
Project-URL: Repository, https://github.com/blueschu/django-htcpcp-tea
